calculator/__init__.py
calculator/addition.py
calculator/division.py
calculator/multiplication.py
calculator/subtraction.py
Modular_programing-1.0.0.dist-info/LICENSE
Modular_programing-1.0.0.dist-info/METADATA
Modular_programing-1.0.0.dist-info/WHEEL
Modular_programing-1.0.0.dist-info/top_level.txt
Modular_programing-1.0.0.dist-info/RECORD
